ctrlutils/__init__.py
ctrlutils/ctrlutils.cpython-310-darwin.so
ctrlutils/ctrlutils_eigen.cpython-310-darwin.so
ctrlutils/numpy.py
ctrlutils/redis.py
ctrlutils/timer.py
ctrlutils/eigen/__init__.py
ctrlutils-1.5.1.dist-info/LICENSE
ctrlutils-1.5.1.dist-info/METADATA
ctrlutils-1.5.1.dist-info/WHEEL
ctrlutils-1.5.1.dist-info/top_level.txt
ctrlutils-1.5.1.dist-info/RECORD
