Metadata-Version: 2.1
Name: ctrlutils
Version: 1.5.1
Summary: Python robot control utils
Author-email: Toki Migimatsu <takatoki@cs.stanford.edu>
License: MIT License
Project-URL: Homepage, https://github.com/tmigimatsu/ctrl-utils.git
Classifier: Programming Language :: Python :: 3
Classifier: License :: OSI Approved :: MIT License
Classifier: Operating System :: OS Independent
Requires-Python: >=3.7
License-File: LICENSE
Requires-Dist: numpy
Requires-Dist: redis
